cloudperf/__init__.py
cloudperf/benchmarks.py
cloudperf/cli.py
cloudperf/core.py
cloudperf/providers/__init__.py
cloudperf/providers/aws.py
cloudperf/providers/aws_helpers.py
cloudperf-0.0.52.dist-info/licenses/LICENSE
cloudperf-0.0.52.dist-info/METADATA
cloudperf-0.0.52.dist-info/WHEEL
cloudperf-0.0.52.dist-info/entry_points.txt
cloudperf-0.0.52.dist-info/top_level.txt
cloudperf-0.0.52.dist-info/RECORD
