Metadata-Version: 2.4
Name: cloudperf
Version: 0.0.52
Summary: Relative performance index for cloud services
Author-email: "NAGY, Attila" <nagy.attila@gmail.com>
Project-URL: Homepage, https://github.com/bra-fsn/cloudperf
Project-URL: Source, https://github.com/bra-fsn/cloudperf
Classifier: Programming Language :: Python
Classifier: License :: OSI Approved :: MIT License
Classifier: Operating System :: OS Independent
Requires-Python: >=3.8
License-File: LICENSE
Requires-Dist: cachetools
Requires-Dist: click>=7.0
Requires-Dist: boto3>=1.9.61
Requires-Dist: pandas
Requires-Dist: requests
Requires-Dist: python-dateutil
Requires-Dist: paramiko
Requires-Dist: pytimeparse
Dynamic: license-file
